{
    "properties": [
      {
        "id": "1",
	      "name": "King",
        "profile": "https://images.pexels.com/photos/614810/pexels-photo-614810.jpeg",
        "ownerType": "Owner",
        "transactionType": "Sale",
        "propertyType": "Flat",
        "description": "Spacious 2BHK flat with a beautiful view.",
        "location": {
          "coordinates": [17.385044, 78.486671],
          "houseNo": "101",
          "street": "Main Street",
          "mandal": "Miyapur",
          "district": "Hyderabad",
          "city": "Hyderabad",
          "state": "Telangana",
          "pincode": "500049"
        },
        "bedrooms": 2,
        "bathrooms": 2,
        "floor": 4,
        "totalFloors": 6,
        "furniture": "Semi Furnitured",
        "yearOfConstruction": 2018,
        "availableFrom": "2023-03",
        "coveredArea": 1200,
        "carpetArea": 1000,
        "amenities": ["Parking", "Gym", "Security"],
        "expectedPrice": 23500,
        "priceIncludes": "Negotiable",
        "advanceDeposit": 50000,
        "stampDuty": true,
        "images": [
          "https://images.pexels.com/photos/53610/large-home-residential-house-architecture-53610.jpeg",
          "https://images.pexels.com/photos/53610/large-home-residential-house-architecture-53610.jpeg",
          "https://images.pexels.com/photos/53610/large-home-residential-house-architecture-53610.jpeg"
        ]
      },
      {
        "id": "2",
	      "name": "King",
        "profile": "https://images.pexels.com/photos/614810/pexels-photo-614810.jpeg",
        "ownerType": "Owner",
        "transactionType": "Sale",
        "propertyType": "House",
        "description": "Beautiful 3BHK house with a garden.",
        "location": {
          "coordinates": [17.385044, 78.486671],
          "houseNo": "356",
          "street": "Main Street",
          "mandal": "Miyapur",
          "district": "Hyderabad",
          "city": "Hyderabad",
          "state": "Telangana",
          "pincode": "500049"
        },
        "bedrooms": 3,
        "bathrooms": 2,
        "floor": 2,
        "totalFloors": 3,
        "furniture": "Unfurnitured",
        "yearOfConstruction": 2015,
        "availableFrom": "2023-04",
        "coveredArea": 1800,
        "carpetArea": 1500,
        "amenities": ["Parking", "Garden", "Power Backup"],
        "expectedPrice": 130000,
        "priceIncludes": "Fixed",
        "advanceDeposit": 100000,
        "stampDuty": false,
        "createdDate": "2023-01-01",
        "lastUpdatedDate": "2023-12-29",
        "images": [
          "https://images.pexels.com/photos/209296/pexels-photo-209296.jpeg",
          "https://images.pexels.com/photos/209296/pexels-photo-209296.jpeg",
          "https://images.pexels.com/photos/209296/pexels-photo-209296.jpeg"
        ]
      },
      {
        "id": "3",
	      "name": "King",
        "profile": "https://images.pexels.com/photos/614810/pexels-photo-614810.jpeg",
        "ownerType": "Owner",
        "transactionType": "Rent",
        "propertyType": "Flat",
        "description": "Spacious 2BHK flat with a beautiful view.",
        "location": {
          "coordinates": [12.971598, 77.594562],
          "houseNo": "302",
          "street": "Park Avenue",
          "mandal": "Banjara Hills",
          "district": "Hyderabad",
          "city": "Hyderabad",
          "state": "Telangana",
          "pincode": "500034"
        },
        "bedrooms": 2,
        "bathrooms": 2,
        "floor": 4,
        "totalFloors": 6,
        "furniture": "Semi Furnitured",
        "yearOfConstruction": 2018,
        "availableFrom": "2023-03",
        "coveredArea": 1200,
        "carpetArea": 1000,
        "amenities": ["Parking", "Gym", "Security"],
        "expectedPrice": 2350,
        "priceIncludes": "Negotiable",
        "advanceDeposit": 50000,
        "stampDuty": true,
        "createdDate": "2023-11-01",
        "lastUpdatedDate": "2023-12-29",
        "images": [
          "https://images.pexels.com/photos/208736/pexels-photo-208736.jpeg",
          "https://images.pexels.com/photos/208736/pexels-photo-208736.jpeg",
          "https://images.pexels.com/photos/208736/pexels-photo-208736.jpeg"
        ]
      },
      {
        "id": "4",
	      "name": "Devil",
        "profile": "https://images.pexels.com/photos/415829/pexels-photo-415829.jpeg",
        "ownerType": "Owner",
        "transactionType": "Rent",
        "propertyType": "Flat",
        "description": "Spacious 2BHK flat with a beautiful view.",
        "location": {
          "coordinates": [28.613939, 77.209023],
          "houseNo": "201",
          "street": "Green Lane",
          "mandal": "Secunderabad",
          "district": "Hyderabad",
          "city": "Hyderabad",
          "state": "Telangana",
          "pincode": "500003"
        },
        "bedrooms": 2,
        "bathrooms": 2,
        "floor": 4,
        "totalFloors": 6,
        "furniture": "Semi Furnitured",
        "yearOfConstruction": 2018,
        "availableFrom": "2023-03",
        "coveredArea": 1200,
        "carpetArea": 1000,
        "amenities": ["Parking", "Gym", "Security"],
        "expectedPrice": 1350,
        "priceIncludes": "Negotiable",
        "advanceDeposit": 50000,
        "stampDuty": true,
        "createdDate": "2023-12-01",
        "lastUpdatedDate": "2023-12-29",
        "images": [
          "https://images.pexels.com/photos/731082/pexels-photo-731082.jpeg",
          "https://images.pexels.com/photos/731082/pexels-photo-731082.jpeg",
          "https://images.pexels.com/photos/731082/pexels-photo-731082.jpeg"
        ]
      },
      {
        "id": "5",
	      "name": "Devil",
        "profile": "https://images.pexels.com/photos/415829/pexels-photo-415829.jpeg",
        "ownerType": "Agent",
        "transactionType": "Sale",
        "propertyType": "Flat",
        "description": "Spacious 2BHK flat with a beautiful view.",
        "location": {
          "coordinates": [25.276987, 83.036500],
          "houseNo": "401",
          "street": "River Road",
          "mandal": "Ameerpet",
          "district": "Hyderabad",
          "city": "Hyderabad",
          "state": "Telangana",
          "pincode": "500016"
        },
        "bedrooms": 2,
        "bathrooms": 2,
        "floor": 4,
        "totalFloors": 6,
        "furniture": "Semi Furnitured",
        "yearOfConstruction": 2018,
        "availableFrom": "2023-03",
        "coveredArea": 1200,
        "carpetArea": 1000,
        "amenities": ["Parking", "Gym", "Security"],
        "expectedPrice": 5605,
        "priceIncludes": "Negotiable",
        "advanceDeposit": 50000,
        "stampDuty": true,
        "createdDate": "2023-12-29",
        "lastUpdatedDate": "2023-12-29",
        "images": [
          "https://images.pexels.com/photos/1396132/pexels-photo-1396132.jpeg",
          "https://images.pexels.com/photos/1396132/pexels-photo-1396132.jpeg",
          "https://images.pexels.com/photos/1396132/pexels-photo-1396132.jpeg"
        ]
      },
      {
        "id": "6",
	      "name": "Devil",
        "profile": "https://images.pexels.com/photos/415829/pexels-photo-415829.jpeg",
        "ownerType": "Agent",
        "transactionType": "Sale",
        "propertyType": "Flat",
        "description": "Spacious 2BHK flat with a beautiful view.",
        "location": {
          "coordinates": [19.076090, 72.877426],
          "houseNo": "501",
          "street": "Ocean View",
          "mandal": "Jubilee Hills",
          "district": "Hyderabad",
          "city": "Hyderabad",
          "state": "Telangana",
          "pincode": "500033"
        },
        "bedrooms": 2,
        "bathrooms": 2,
        "floor": 4,
        "totalFloors": 6,
        "furniture": "Semi Furnitured",
        "yearOfConstruction": 2018,
        "availableFrom": "2023-03",
        "coveredArea": 1200,
        "carpetArea": 1000,
        "amenities": ["Parking", "Gym", "Security"],
        "expectedPrice": 6500,
        "priceIncludes": "Negotiable",
        "advanceDeposit": 50000,
        "stampDuty": true,
        "createdDate": "2023-01-01",
        "lastUpdatedDate": "2023-12-02",
        "images": [
          "https://images.pexels.com/photos/1438832/pexels-photo-1438832.jpeg",
          "https://images.pexels.com/photos/1438832/pexels-photo-1438832.jpeg",
          "https://images.pexels.com/photos/1438832/pexels-photo-1438832.jpeg"
        ]
      },
      {
        "id": "7",
	      "name": "Kali",
        "profile": "https://images.pexels.com/photos/2379005/pexels-photo-2379005.jpeg",
        "ownerType": "Agent",
        "transactionType": "Rent",
        "propertyType": "Flat",
        "description": "Spacious 2BHK flat with a beautiful view.",
        "location": {
          "coordinates": [22.572646, 88.363895],
          "houseNo": "601",
          "street": "Skyline Avenue",
          "mandal": "Kukatpally",
          "district": "Hyderabad",
          "city": "Hyderabad",
          "state": "Telangana",
          "pincode": "500072"
        },
        "bedrooms": 2,
        "bathrooms": 2,
        "floor": 4,
        "totalFloors": 6,
        "furniture": "Semi Furnitured",
        "yearOfConstruction": 2018,
        "availableFrom": "2023-03",
        "coveredArea": 1200,
        "carpetArea": 1000,
        "amenities": ["Parking", "Gym", "Security"],
        "expectedPrice": 8950,
        "priceIncludes": "Negotiable",
        "advanceDeposit": 50000,
        "stampDuty": true,
        "createdDate": "2023-01-01",
        "lastUpdatedDate": "2023-12-09",
        "images": [
          "https://images.pexels.com/photos/164558/pexels-photo-164558.jpeg",
          "https://images.pexels.com/photos/164558/pexels-photo-164558.jpeg",
          "https://images.pexels.com/photos/164558/pexels-photo-164558.jpeg"
        ]
      },
      {
        "id": "8",
	      "name": "Kali",
        "profile": "https://images.pexels.com/photos/2379005/pexels-photo-2379005.jpeg",
        "ownerType": "Agent",
        "transactionType": "Rent",
        "propertyType": "Flat",
        "description": "Spacious 2BHK flat with a beautiful view.",
        "location": {
          "coordinates": [23.022505, 72.571365],
          "houseNo": "701",
          "street": "Sunrise Lane",
          "mandal": "Begumpet",
          "district": "Hyderabad",
          "city": "Hyderabad",
          "state": "Telangana",
          "pincode": "500016"
        },
        "bedrooms": 2,
        "bathrooms": 2,
        "floor": 4,
        "totalFloors": 6,
        "furniture": "Semi Furnitured",
        "yearOfConstruction": 2018,
        "availableFrom": "2023-03",
        "coveredArea": 1200,
        "carpetArea": 1000,
        "amenities": ["Parking", "Gym", "Security"],
        "expectedPrice": 4560,
        "priceIncludes": "Negotiable",
        "advanceDeposit": 50000,
        "stampDuty": true,
        "createdDate": "2023-01-01",
        "lastUpdatedDate": "2023-12-28",
        "images": [
          "https://images.pexels.com/photos/259588/pexels-photo-259588.jpeg",
          "https://images.pexels.com/photos/259588/pexels-photo-259588.jpeg",
          "https://images.pexels.com/photos/259588/pexels-photo-259588.jpeg"
        ]
      },
      {
        "id": "9",
	      "name": "Kali",
        "profile": "https://images.pexels.com/photos/2379005/pexels-photo-2379005.jpeg",
        "ownerType": "Owner",
        "transactionType": "Rent",
        "propertyType": "Flat",
        "description": "Spacious 2BHK flat with a beautiful view.",
        "location": {
          "coordinates": [13.082680, 80.270718],
          "houseNo": "801",
          "street": "Sunset Boulevard",
          "mandal": "HITEC City",
          "district": "Hyderabad",
          "city": "Hyderabad",
          "state": "Telangana",
          "pincode": "500081"
        },
        "bedrooms": 2,
        "bathrooms": 2,
        "floor": 4,
        "totalFloors": 6,
        "furniture": "Semi Furnitured",
        "yearOfConstruction": 2018,
        "availableFrom": "2023-03",
        "coveredArea": 1200,
        "carpetArea": 1000,
        "amenities": ["Parking", "Gym", "Security"],
        "expectedPrice": 16859,
        "priceIncludes": "Negotiable",
        "advanceDeposit": 50000,
        "stampDuty": true,
        "createdDate": "2023-01-01",
        "lastUpdatedDate": "2023-12-27",
        "images": [
          "https://images.pexels.com/photos/1396122/pexels-photo-1396122.jpeg",
          "https://images.pexels.com/photos/1396122/pexels-photo-1396122.jpeg",
          "https://images.pexels.com/photos/1396122/pexels-photo-1396122.jpeg"
        ]
      },
      {
        "id": "10",
	      "name": "Mani",
        "profile": "https://images.pexels.com/photos/2169434/pexels-photo-2169434.jpeg",
        "ownerType": "Owner",
        "transactionType": "Rent",
        "propertyType": "Flat",
        "description": "Spacious 2BHK flat with a beautiful view.",
        "location": {
          "coordinates": [28.704060, 77.102493],
          "houseNo": "901",
          "street": "Lakeside Drive",
          "mandal": "Gachibowli",
          "district": "Hyderabad",
          "city": "Hyderabad",
          "state": "Telangana",
          "pincode": "500055"
        },
        "bedrooms": 2,
        "bathrooms": 2,
        "floor": 4,
        "totalFloors": 6,
        "furniture": "Semi Furnitured",
        "yearOfConstruction": 2018,
        "availableFrom": "2023-03",
        "coveredArea": 1200,
        "carpetArea": 1000,
        "amenities": ["Parking", "Gym", "Security"],
        "expectedPrice": 1469530,
        "priceIncludes": "Negotiable",
        "advanceDeposit": 50000,
        "stampDuty": true,
        "createdDate": "2023-01-01",
        "lastUpdatedDate": "2023-12-26",
        "images": [
          "https://images.pexels.com/photos/323780/pexels-photo-323780.jpeg",
          "https://images.pexels.com/photos/323780/pexels-photo-323780.jpeg",
          "https://images.pexels.com/photos/323780/pexels-photo-323780.jpeg"
        ]
      },
      {
        "id": "11",
	      "name": "Mani",
        "profile": "https://images.pexels.com/photos/2169434/pexels-photo-2169434.jpeg",
        "ownerType": "Agent",
        "transactionType": "Rent",
        "propertyType": "Flat",
        "description": "Spacious 2BHK flat with a beautiful view.",
        "location": {
          "coordinates": [17.447708, 78.491684],
          "houseNo": "1001",
          "street": "Mountain View",
          "mandal": "Madhapur",
          "district": "Hyderabad",
          "city": "Hyderabad",
          "state": "Telangana",
          "pincode": "500055"
        },
        "bedrooms": 3,
        "bathrooms": 2,
        "floor": 4,
        "totalFloors": 6,
        "furniture": "Semi Furnitured",
        "yearOfConstruction": 2018,
        "availableFrom": "2023-03",
        "coveredArea": 1200,
        "carpetArea": 1000,
        "amenities": ["Parking", "Gym", "Security"],
        "expectedPrice": 16530,
        "priceIncludes": "Negotiable",
        "advanceDeposit": 5000,
        "stampDuty": true,
        "createdDate": "2023-01-01",
        "lastUpdatedDate": "2023-12-27",
        "images": [
          "https://images.pexels.com/photos/106399/pexels-photo-106399.jpeg",
          "https://images.pexels.com/photos/186077/pexels-photo-186077.jpeg",
          "https://images.pexels.com/photos/186077/pexels-photo-186077.jpeg"
        ]
      }
    ]
  }
  